README.md
setup.py
ngao/__init__.py
ngao/cli.py
ngao.egg-info/PKG-INFO
ngao.egg-info/SOURCES.txt
ngao.egg-info/dependency_links.txt
ngao.egg-info/entry_points.txt
ngao.egg-info/requires.txt
ngao.egg-info/top_level.txt
ngao/commands/__init__.py
ngao/commands/billing.py
ngao/commands/config.py
ngao/commands/http.py
ngao/commands/secure.py
ngao/commands/subdomain.py
ngao/commands/tcp.py
ngao/commands/tunnel.py
ngao/commands/udp.py
ngao/commands/utils.py
ngao/commands/vpn.py