Metadata-Version: 2.1
Name: ngao
Version: 0.3.0
Summary: NGAO - Tunnel local ports to public URLs and inspect traffic
Home-page: https://github.com/yourusername/ngao
Author: Mark Francis / Masasi Mgengeli 
Author-email: support@ngao.pro
Classifier: Programming Language :: Python :: 3
Classifier: License :: OSI Approved :: MIT License
Classifier: Operating System :: OS Independent
Requires-Python: >=3.6
Requires-Dist: ngiri
